avela/__init__.py
avela/__version__.py
avela/auth.py
avela/client.py
avela/exceptions.py
avela/py.typed
avela/resources.py
avela-0.1.0.dist-info/licenses/LICENSE
avela-0.1.0.dist-info/METADATA
avela-0.1.0.dist-info/WHEEL
avela-0.1.0.dist-info/top_level.txt
avela-0.1.0.dist-info/RECORD
