Metadata-Version: 2.4
Name: avela
Version: 0.1.0
Summary: Official Python SDK for the Avela Education Platform API
Author-email: Avela Education <support@avela.org>
License: MIT
Project-URL: Homepage, https://github.com/Avela-Education/avela-python
Project-URL: Repository, https://github.com/Avela-Education/avela-python
Project-URL: Bug Tracker, https://github.com/Avela-Education/avela-python/issues
Keywords: avela,education,api,sdk
Classifier: Development Status :: 3 - Alpha
Classifier: Intended Audience :: Developers
Classifier: License :: OSI Approved :: MIT License
Classifier: Programming Language :: Python :: 3
Classifier: Programming Language :: Python :: 3.10
Classifier: Programming Language :: Python :: 3.11
Classifier: Programming Language :: Python :: 3.12
Classifier: Topic :: Software Development :: Libraries :: Python Modules
Requires-Python: >=3.10
License-File: LICENSE
Requires-Dist: requests>=2.31.0
Provides-Extra: dev
Requires-Dist: pytest>=7.4.0; extra == "dev"
Requires-Dist: pytest-cov>=4.1.0; extra == "dev"
Requires-Dist: black>=23.7.0; extra == "dev"
Requires-Dist: ruff>=0.0.285; extra == "dev"
Requires-Dist: mypy>=1.5.0; extra == "dev"
Requires-Dist: types-requests>=2.31.0; extra == "dev"
Dynamic: license-file
